input_devices/__init__.py
input_devices-0.1.2.dist-info/LICENSE
input_devices-0.1.2.dist-info/METADATA
input_devices-0.1.2.dist-info/WHEEL
input_devices-0.1.2.dist-info/top_level.txt
input_devices-0.1.2.dist-info/RECORD
