Metadata-Version: 2.1
Name: input-devices
Version: 0.1.2
Summary: High level API wrapper around inputs library for working with input devices like gamepads, joysticks, etc.
Home-page: https://github.com/MarikTik/input_devices
Author: Mark Tikhonov
Author-email: mtik.philosopher@gmail.com
License: MIT
Platform: UNKNOWN
Classifier: Development Status :: 3 - Alpha
Classifier: Intended Audience :: Developers
Classifier: License :: OSI Approved :: MIT License
Classifier: Programming Language :: Python :: 3
License-File: LICENSE
Requires-Dist: inputs
